.coveragerc
.gitignore
.travis.yml
MANIFEST.in
README.rst
base.cfg
bootstrap.py
buildout.cfg
setup.py
travis.cfg
collective/__init__.py
collective.sugarcrm.egg-info/PKG-INFO
collective.sugarcrm.egg-info/SOURCES.txt
collective.sugarcrm.egg-info/dependency_links.txt
collective.sugarcrm.egg-info/entry_points.txt
collective.sugarcrm.egg-info/namespace_packages.txt
collective.sugarcrm.egg-info/not-zip-safe
collective.sugarcrm.egg-info/requires.txt
collective.sugarcrm.egg-info/top_level.txt
collective/sugarcrm/__init__.py
collective/sugarcrm/configure.zcml
collective/sugarcrm/controlpanel.py
collective/sugarcrm/interfaces.py
collective/sugarcrm/pasplugin.py
collective/sugarcrm/password.py
collective/sugarcrm/portlet.py
collective/sugarcrm/profiles.zcml
collective/sugarcrm/setuphandlers.py
collective/sugarcrm/source.py
collective/sugarcrm/sugarcrm.gif
collective/sugarcrm/testing.py
collective/sugarcrm/upgrades.py
collective/sugarcrm/upgrades.zcml
collective/sugarcrm/webservice.py
collective/sugarcrm/z3c_suds.py
collective/sugarcrm/profiles/default/controlpanel.xml
collective/sugarcrm/profiles/default/metadata.xml
collective/sugarcrm/profiles/default/propertiestool.xml
collective/sugarcrm/profiles/default/sugarcrm.txt
collective/sugarcrm/tests/__init__.py
collective/sugarcrm/tests/base.py
collective/sugarcrm/tests/test_pas_plugins.py
collective/sugarcrm/tests/test_webservice.py
collective/sugarcrm/tests/utils.py
docs/HISTORY.txt
docs/INSTALL.txt
docs/LICENSE.GPL
docs/LICENSE.txt